{"is_source_file": true, "format": "JavaScript", "description": "This source file initializes and exports a Supabase client instance using environment variables. It sets up the connection to the Supabase backend for authentication and database operations within a React application.", "external_files": ["@supabase/supabase-js"], "external_methods": ["createClient"], "published": ["supabase"], "classes": [], "methods": [], "calls": ["createClient"], "search-terms": ["supabase", "createClient", "environment variables", "React_APP_SUPABASE"], "state": 2, "file_id": 14, "knowledge_revision": 30, "git_revision": "", "ctags": [{"_type": "tag", "name": "supabase", "path": "/home/kavia/workspace/code-generation/simple-to-do-manager-03425b5b/frontend_app/src/supabaseClient.js", "pattern": "/^export const supabase = createClient(supabaseUrl, supabaseAnonKey);$/", "language": "JavaScript", "kind": "constant"}, {"_type": "tag", "name": "supabaseAnonKey", "path": "/home/kavia/workspace/code-generation/simple-to-do-manager-03425b5b/frontend_app/src/supabaseClient.js", "pattern": "/^const supabaseAnonKey = process.env.REACT_APP_SUPABASE_KEY;$/", "language": "JavaScript", "kind": "constant"}, {"_type": "tag", "name": "supabaseUrl", "path": "/home/kavia/workspace/code-generation/simple-to-do-manager-03425b5b/frontend_app/src/supabaseClient.js", "pattern": "/^const supabaseUrl = process.env.REACT_APP_SUPABASE_URL;$/", "language": "JavaScript", "kind": "constant"}], "hash": "b1c6f74cc68b3608426207fabb835e13", "format-version": 4, "code-base-name": "frontend_app", "filename": "frontend_app/src/supabaseClient.js", "revision_history": [{"30": ""}]}